AUTHORS
CHANGES
README
setup.py
django_genericforeignkey.egg-info/PKG-INFO
django_genericforeignkey.egg-info/SOURCES.txt
django_genericforeignkey.egg-info/dependency_links.txt
django_genericforeignkey.egg-info/not-zip-safe
django_genericforeignkey.egg-info/top_level.txt
genericforeignkey/__init__.py
genericforeignkey/admin.py
genericforeignkey/admin_register.py
genericforeignkey/fields.py
genericforeignkey/forms.py
genericforeignkey/urls.py
genericforeignkey/utils.py
genericforeignkey/views.py
genericforeignkey/widgets.py
genericforeignkey/locale/en/LC_MESSAGES/django.po
genericforeignkey/locale/es/LC_MESSAGES/django.po
genericforeignkey/media/css/genericforeignkey.css
genericforeignkey/media/img/cancel.png
genericforeignkey/media/img/current_page.jpg
genericforeignkey/media/img/next_page.jpg
genericforeignkey/media/img/page.jpg
genericforeignkey/media/img/prev_page.jpg
genericforeignkey/media/js/content_type_object.js
genericforeignkey/media/js/genericforeignkeywidget_public.js
genericforeignkey/media/js/jquery.genericforeignkeywidget.js
genericforeignkey/templates/genericforeignkey/object_list.html