Metadata-Version: 1.0
Name: django-genericforeignkey
Version: 0.60.4
Summary: Django application that allows yo yout generic relations have a nice admin widget
Home-page: http://tracpub.yaco.es/djangoapps/wiki/GenericForeignKey
Author: Yaco Sistemas S.L.
Author-email: pmartin@yaco.es
License: LGPL 3
Keywords: django generic relations
Platform: UNKNOWN
Classifier: Development Status :: 4 - Beta
Classifier: Framework :: Django
Classifier: License :: OSI Approved :: GNU Library or Lesser General Public License (LGPL)
